decomply/__init__.py
decomply/decomply.py
decomply/enumerable.py
decomply/tests/__init__.py
decomply/tests/test.py
decomply-1.1.2.dist-info/METADATA
decomply-1.1.2.dist-info/WHEEL
decomply-1.1.2.dist-info/top_level.txt
decomply-1.1.2.dist-info/RECORD
