Metadata-Version: 2.1
Name: decomply
Version: 1.1.2
Summary: decomply allows unified processing of nested dictionaries
Home-page: https://github.com/truekenji/decomply
Author: TrueKenji
Keywords: Dictionary,Recursive,Traverse,Apply,Decompose,Partition,Nested,Loop,List,JSON
Classifier: Programming Language :: Python :: 3
Classifier: License :: OSI Approved :: MIT License
Classifier: Operating System :: OS Independent
Requires-Dist: numpy
